bw2parameters/__init__.py
bw2parameters/errors.py
bw2parameters/interpreter.py
bw2parameters/mangling.py
bw2parameters/parameter_set.py
bw2parameters/pint.py
bw2parameters/utils.py
docs/conf.py
bw2parameters-1.1.0.dist-info/LICENSE
bw2parameters-1.1.0.dist-info/METADATA
bw2parameters-1.1.0.dist-info/WHEEL
bw2parameters-1.1.0.dist-info/top_level.txt
bw2parameters-1.1.0.dist-info/RECORD
