Metadata-Version: 2.1
Name: bw2parameters
Version: 1.1.0
Summary: Contains all the python boilerplate you need to create a Brightway ecosystem package.
Home-page: https://github.com/brightway-lca/brightway2-parameters
Author: Chris Mutel
Author-email: <cmutel@gmail.com>
Maintainer: Chris Mutel
Maintainer-email: <cmutel@gmail.com>
License: BSD-3-Clause
Project-URL: source, https://github.com/brightway-lca/brightway2-parameters
Project-URL: homepage, https://github.com/brightway-lca/brightway2-parameters
Project-URL: tracker, https://github.com/brightway-lca/brightway2-parameters/issues
Keywords: "brightway","development"
Platform: any
Classifier: Development Status :: 5 - Production/Stable
Classifier: Programming Language :: Python
Classifier: Programming Language :: Python :: 3
Classifier: Programming Language :: Python :: 3.8
Classifier: Programming Language :: Python :: 3.9
Classifier: Programming Language :: Python :: 3.10
Classifier: Programming Language :: Python :: 3.11
Requires-Python: >=3.8
Provides-Extra: testing
Provides-Extra: dev
Provides-Extra: docs
License-File: LICENSE
